inventory_card_reader/__init__.py
inventory_card_reader/read_directory.py
inventory_card_reader/processors/__init__.py
inventory_card_reader/processors/image_detector.py
inventory_card_reader/processors/page_xml_parser.py
inventory_card_reader/processors/pero_ocr_processor.py
inventory_card_reader/processors/postprocessor.py
inventory_card_reader/processors/utils.py
inventory_card_reader-0.0.16.dist-info/METADATA
inventory_card_reader-0.0.16.dist-info/WHEEL
inventory_card_reader-0.0.16.dist-info/entry_points.txt
inventory_card_reader-0.0.16.dist-info/top_level.txt
inventory_card_reader-0.0.16.dist-info/RECORD
