Metadata-Version: 2.1
Name: inventory-card-reader
Version: 0.0.16
Summary: Read, process, and integrate data from inventory cards.
Author-email: Mathias Zinnen <mathias.zinnen@gmail.com>
Project-URL: Homepage, https://github.com/mathiaszinnen/inventory-card-reader
Project-URL: Issues, https://github.com/mathiaszinnen/inventory-card-reader/issues
Classifier: Programming Language :: Python :: 3
Classifier: License :: OSI Approved :: MIT License
Classifier: Operating System :: OS Independent
Requires-Python: >=3.8
Requires-Dist: pero-ocr
Requires-Dist: pyyaml
Requires-Dist: pandas
Requires-Dist: tqdm
Requires-Dist: ultralytics
Requires-Dist: appdirs
